pytfa/__init__.py
pytfa/analysis/__init__.py
pytfa/analysis/chebyshev.py
pytfa/analysis/manipulation.py
pytfa/analysis/sampling.py
pytfa/analysis/variability.py
pytfa/core/__init__.py
pytfa/core/model.py
pytfa/io/__init__.py
pytfa/io/base.py
pytfa/io/dict.py
pytfa/io/enrichment.py
pytfa/io/json.py
pytfa/io/plotting.py
pytfa/io/viz.py
pytfa/optim/__init__.py
pytfa/optim/config.py
pytfa/optim/constraints.py
pytfa/optim/debugging.py
pytfa/optim/meta.py
pytfa/optim/reformulation.py
pytfa/optim/relaxation.py
pytfa/optim/utils.py
pytfa/optim/variables.py
pytfa/redgem/__init__.py
pytfa/redgem/debugging.py
pytfa/redgem/lumpgem.py
pytfa/redgem/network_expansion.py
pytfa/redgem/redgem.py
pytfa/redgem/utils.py
pytfa/thermo/__init__.py
pytfa/thermo/equilibrator.py
pytfa/thermo/metabolite.py
pytfa/thermo/reaction.py
pytfa/thermo/std.py
pytfa/thermo/tmodel.py
pytfa/thermo/utils.py
pytfa/utils/__init__.py
pytfa/utils/logger.py
pytfa/utils/numerics.py
pytfa/utils/str.py
pytfa-0.9.4.dist-info/LICENSE.txt
pytfa-0.9.4.dist-info/METADATA
pytfa-0.9.4.dist-info/WHEEL
pytfa-0.9.4.dist-info/top_level.txt
pytfa-0.9.4.dist-info/RECORD
